.stestr.conf
AUTHORS
ChangeLog
LICENSE
README.rst
requirements.txt
setup.cfg
setup.py
test-requirements.txt
tox.ini
pymqttbench/__init__.py
pymqttbench/bench.py
pymqttbench.egg-info/PKG-INFO
pymqttbench.egg-info/SOURCES.txt
pymqttbench.egg-info/dependency_links.txt
pymqttbench.egg-info/entry_points.txt
pymqttbench.egg-info/not-zip-safe
pymqttbench.egg-info/pbr.json
pymqttbench.egg-info/requires.txt
pymqttbench.egg-info/top_level.txt
pymqttbench/tests/__init__.py
pymqttbench/tests/test_bench.py