Metadata-Version: 1.1
Name: pymqttbench
Version: 0.1.1
Summary: A script to benchmark an MQTT broker
Home-page: UNKNOWN
Author: Matthew Treinish
Author-email: mtreinish@kortar.org
License: UNKNOWN
Platform: UNKNOWN
Classifier: Intended Audience :: Information Technology
Classifier: Intended Audience :: System Administrators
Classifier: License :: OSI Approved :: Apache Software License
Classifier: Programming Language :: Python
Classifier: Programming Language :: Python :: 2
Classifier: Programming Language :: Python :: 2.7
Classifier: Programming Language :: Python :: 3
Classifier: Programming Language :: Python :: 3.5
Classifier: Programming Language :: Python :: 3.6
